bmc/__init__.py
bmc/_bmc.so
bmc/bmc.py
kbench/__init__.py
kbench/classes/__init__.py
kbench/classes/deformable_mirror.py
kbench/classes/filter_wheel.py
kbench/classes/kernel.py
kbench/classes/pupil_mask.py
kbench/sandbox/__init__.py
kbench/sandbox/bmc_mock.py
kbench/sandbox/serial_mock.py
kbench_controls-0.7.1.dist-info/METADATA
kbench_controls-0.7.1.dist-info/WHEEL
kbench_controls-0.7.1.dist-info/entry_points.txt
kbench_controls-0.7.1.dist-info/RECORD
