Metadata-Version: 2.1
Name: kbench-controls
Version: 0.7.1
Summary: Default template for PDM package
Author-Email: Vincent Foriel <vincent.foriel@gmail.com>, mmartinod <ma.martinod@free.fr>
License: MIT
Requires-Python: ==3.12.*
Requires-Dist: numpy
Requires-Dist: pyserial
Requires-Dist: pyyaml
Requires-Dist: toml>=0.10.2
